e2e/env/__init__.py
e2e/env/exceptions.py
e2e.env-0.1.0.dist-info/LICENSE
e2e.env-0.1.0.dist-info/METADATA
e2e.env-0.1.0.dist-info/WHEEL
e2e.env-0.1.0.dist-info/top_level.txt
e2e.env-0.1.0.dist-info/RECORD
